pophacks/consts.py
pophacks/monkeytype/__init__.py
pophacks-1.0.0.data/scripts/pophacks
pophacks-1.0.0.dist-info/METADATA
pophacks-1.0.0.dist-info/WHEEL
pophacks-1.0.0.dist-info/top_level.txt
pophacks-1.0.0.dist-info/RECORD
